risset.py
risset-3.2.2.dist-info/METADATA
risset-3.2.2.dist-info/WHEEL
risset-3.2.2.dist-info/entry_points.txt
risset-3.2.2.dist-info/top_level.txt
risset-3.2.2.dist-info/RECORD
