Metadata-Version: 2.4
Name: risset
Version: 3.2.2
Summary: Package manager for csound
Author-email: Eduardo Moguillansky <eduardo.moguillansky@gmail.com>
Project-URL: Homepage, https://github.com/csound-plugins/risset
Keywords: csound
Classifier: Topic :: Multimedia :: Sound/Audio
Classifier: Programming Language :: Python :: 3
Classifier: Operating System :: OS Independent
Requires-Python: >=3.9
Requires-Dist: pygments
Requires-Dist: libcsound>=0.9.1
Requires-Dist: mkdocs
Requires-Dist: requests
Requires-Dist: filetype
